<?xml version="1.0" encoding="UTF-8"?>
<timelime id="treeholes">
    <status>
        <text><![CDATA[一个还不错的朋友，稍有暧昧，一次一起走的时候我们都没有说话，他忽然蹦出一句，人生若只如初见，什么意思啊他是。]]></text>
        <time><![CDATA[2012-03-15 18:06:00]]></time>
    </status>

    <status>
        <text><![CDATA[我自卑到不敢钟意人，因为公事我得到了她的手机号，在想如果能看到她微薄更好，于是搜她手机号，真被我搜到微博了，美丽大方开朗懂礼声甜肤好学历高职位高有钱有车有房有男友，而最重要的是我们性别相同]]></text>
        <time><![CDATA[2012-03-15 17:59:02]]></time>
    </status>

    <status>
        <text><![CDATA[跟前男友分手了将近两年了 后来我们做了偶尔还能聊聊天的朋友 挺知心的 但是听说他跟他现任感情很好不知道为嘛虽然嘴上说着祝福替他感到开心 但是心里就是高兴不起来 明明早就已经放下他了 难道是嫉妒心在作祟…]]></text>
        <time><![CDATA[2012-03-15 17:25:02]]></time>
    </status>

    <status>
        <text><![CDATA[内置的不挺好么？]]></text>
        <time><![CDATA[2012-03-15 17:23:02]]></time>
    </status>

    <status>
        <text><![CDATA[字典下了是mobi格式，没有办法列入Kindle的字典列单更别说选作默认字典了，肿摸办呀嘤嘤嘤，]]></text>
        <time><![CDATA[2012-03-15 17:18:02]]></time>
    </status>

    <status>
        <text><![CDATA[#说个笑话#两人吃饭，桌上放着一碗芥末。其中一个认为是甜的，舀了满满一勺放进嘴里，立即泪如泉涌，不过他紧闭嘴巴没说一句话。朋友问怎么了。他说：想我爹了，20年前的今天他上吊了。朋友安慰了他，也舀了满满一勺放进嘴里，骤然泪如雨下。第一位问：你怎么也哭了？朋友说：你爹死得好惨。]]></text>
        <time><![CDATA[2012-03-15 16:48:01]]></time>
    </status>

    <status>
        <text><![CDATA[每天都在心里说爱你，我现在没有资格对你说，我还在追求人身自由的路上艰难前进着……]]></text>
        <time><![CDATA[2012-03-15 16:30:03]]></time>
    </status>

    <status>
        <text><![CDATA[微信很可怕的。。。]]></text>
        <time><![CDATA[2012-03-15 16:10:02]]></time>
    </status>

    <status>
        <text><![CDATA[洞啊，本人女，最近摔伤了卧床休息，男友每天来看我，我却还是觉得各种空虚寂寞冷，于是去微信捡瓶子，捡到一个很聊得来的男的，男友不在的时候我就一直和他各种聊，什么都聊，包括做爱。我是疯了吗？]]></text>
        <time><![CDATA[2012-03-15 16:03:00]]></time>
    </status>

    <status>
        <text><![CDATA[这么晚了，你在和谁聊呢，好想知道，聊的开心么，他好么，符合你么]]></text>
        <time><![CDATA[2012-03-15 15:54:02]]></time>
    </status>

    <status>
        <text><![CDATA[真正紧张一个人根本不是像你这样的]]></text>
        <time><![CDATA[2012-03-15 15:24:02]]></time>
    </status>

    <status>
        <text><![CDATA[我跟我们学校一个学长在网上认识了一年多,彼此加了人人,都知道名字,但是没见过面,最近我们每晚都聊,其实也是我贱,感觉最近有点暧昧了,昨晚还打了电话,可是他有女朋友,树洞你说怎么办,其实我只是想做普通朋友,现在每晚不找他,我都觉得难受,怎么办啊]]></text>
        <time><![CDATA[2012-03-15 15:23:02]]></time>
    </status>

    <status>
        <text><![CDATA[我是傻逼，从去年开始，常常流连烟花柳巷，本来计划攒起来要给妻子买平板的钱败的一干二净，还欠下卡债，对自己厌恶到极点]]></text>
        <time><![CDATA[2012-03-15 15:17:02]]></time>
    </status>

    <status>
        <text><![CDATA[又被搭讪了 总是遇到怪人]]></text>
        <time><![CDATA[2012-03-15 15:16:00]]></time>
    </status>

    <status>
        <text><![CDATA[我是个双性恋，我一直回避不承认这件事，我最长的恋爱不是一年半，而是大概有七年半了。我是双性恋，真正的双性恋。]]></text>
        <time><![CDATA[2012-03-15 15:14:01]]></time>
    </status>

    <status>
        <text><![CDATA[老子身份证丢了！！放在钱包里没了！！！艹]]></text>
        <time><![CDATA[2012-03-15 15:05:01]]></time>
    </status>

    <status>
        <text><![CDATA[来树洞日常一下，不能浪费~]]></text>
        <time><![CDATA[2012-03-15 15:01:03]]></time>
    </status>

    <status>
        <text><![CDATA[我们离婚吧，趁现在还没有孩子，趁现在还年轻，房子卖了，分一分，各找各的新生活吧]]></text>
        <time><![CDATA[2012-03-15 15:01:02]]></time>
    </status>

    <status>
        <text><![CDATA[大连哪家婚纱照拍的好？]]></text>
        <time><![CDATA[2012-03-15 14:25:03]]></time>
    </status>

    <status>
        <text><![CDATA[你喜欢看惊悚片，惊悚的时候却总是埋头在我背后，手捂着我的眼睛拍我也会怕。]]></text>
        <time><![CDATA[2012-03-15 14:25:02]]></time>
    </status>

    <status>
        <text><![CDATA[我想彻底忘记她，一点记忆都不剩]]></text>
        <time><![CDATA[2012-03-15 14:19:02]]></time>
    </status>

    <status>
        <text><![CDATA[我想去机场送你，但是我没资格了，以前有资格的时候你也老说不让送要挑我上班上课的时候飞走。但是在那之前你的心就飞走了，或者说从来没飞到我这里来过。]]></text>
        <time><![CDATA[2012-03-15 14:13:02]]></time>
    </status>

    <status>
        <text><![CDATA[我好想你，想我们以前在一起的时候，你可不可以再回到我身边呢，不想只做朋友阿]]></text>
        <time><![CDATA[2012-03-15 13:49:02]]></time>
    </status>

    <status>
        <text><![CDATA[老白，鞋子一大早就收到了，谢谢你，我没有淘宝，一直想买你家的鞋，想起表姐有淘宝就让她帮我买了，我知你是不包邮的，在旺旺上和你讲价的是我表姐，鞋子很快到了已经试穿很好看，发到这里希望你能看到，饭友中也还有相信你的陌生人，希望你的感冒赶快好早日康复]]></text>
        <time><![CDATA[2012-03-15 13:36:02]]></time>
    </status>

    <status>
        <text><![CDATA[如果你遇到了正确的人。我就快要成功啦(*/ω＼*)]]></text>
        <time><![CDATA[2012-03-15 13:28:02]]></time>
    </status>

    <status>
        <text><![CDATA[网恋是不是真的很不靠谱。。我很迷茫]]></text>
        <time><![CDATA[2012-03-15 13:24:03]]></time>
    </status>

    <status>
        <text><![CDATA[万能的饭否  求合体]]></text>
        <time><![CDATA[2012-03-15 13:23:02]]></time>
    </status>

    <status>
        <text><![CDATA[万能的饭否 求CAESAR II 5.1以上版本，管道应力分析软件，破解版  邮箱429669469#qq.com 谢谢！]]></text>
        <time><![CDATA[2012-03-15 13:19:01]]></time>
    </status>

    <status>
        <text><![CDATA[宝宝 我想你了 我没吃晚饭  减肥 你要多吃点哈 我不跟你抢]]></text>
        <time><![CDATA[2012-03-15 13:00:03]]></time>
    </status>

    <status>
        <text><![CDATA[电骡资源怎么打不开了]]></text>
        <time><![CDATA[2012-03-15 12:49:02]]></time>
    </status>

    <status>
        <text><![CDATA[半年做了100多次爱这样好不好啊？]]></text>
        <time><![CDATA[2012-03-15 12:28:02]]></time>
    </status>

    <status>
        <text><![CDATA[联通信号真差，一下雨就不行了]]></text>
        <time><![CDATA[2012-03-15 12:22:02]]></time>
    </status>

    <status>
        <text><![CDATA[发现有点喜欢上陈小兔几了。。。]]></text>
        <time><![CDATA[2012-03-15 10:00:02]]></time>
    </status>

    <status>
        <text><![CDATA[对着多晴的照片打飞机，too]]></text>
        <time><![CDATA[2012-03-15 09:57:02]]></time>
    </status>

    <status>
        <text><![CDATA[啊。春天到啦。阳光灿烂。我滴满身肥肉也要现身啦！！！！！]]></text>
        <time><![CDATA[2012-03-15 09:35:02]]></time>
    </status>

    <status>
        <text><![CDATA[对着多晴.姐的照片打飞机了....~~~~(&gt;_&lt;)~~~~]]></text>
        <time><![CDATA[2012-03-15 09:17:02]]></time>
    </status>

    <status>
        <text><![CDATA[新浪实名制是明天开始吗？]]></text>
        <time><![CDATA[2012-03-15 08:42:02]]></time>
    </status>

    <status>
        <text><![CDATA[啊啊啊～～～一天一条什么的，每天都不能浪费～～～]]></text>
        <time><![CDATA[2012-03-15 08:33:00]]></time>
    </status>

    <status>
        <text><![CDATA[我发现姨妈的颜色很美~~是不是很变态]]></text>
        <time><![CDATA[2012-03-15 08:18:02]]></time>
    </status>

    <status>
        <text><![CDATA[我也来miss一下jasmin吧……………………]]></text>
        <time><![CDATA[2012-03-15 08:14:01]]></time>
    </status>

    <status>
        <text><![CDATA[前几天跟一姑娘说我喜欢她，但其实不是真心的，想找个时间道歉，结果她入戏了，我又不想伤害她...我该怎么办啊！]]></text>
        <time><![CDATA[2012-03-15 08:09:03]]></time>
    </status>

    <status>
        <text><![CDATA[每次看岛国AV都觉得特别不尊重女性 女孩子都是被欺负的 看欧美就觉得女的也是有主动权的 不像被摆布的。。。]]></text>
        <time><![CDATA[2012-03-15 08:09:02]]></time>
    </status>

    <status>
        <text><![CDATA[Jasmin, I miss u.  tootootoo.hahaha.]]></text>
        <time><![CDATA[2012-03-15 08:02:03]]></time>
    </status>

    <status>
        <text><![CDATA[樹洞現在還是改成一天一條了麼？試試。以前有段時間是一小時一條的。貌似。]]></text>
        <time><![CDATA[2012-03-15 07:38:02]]></time>
    </status>

    <status>
        <text><![CDATA[既然一天一条,增大了我抢70000的难度。。。。]]></text>
        <time><![CDATA[2012-03-15 07:11:01]]></time>
    </status>

    <status>
        <text><![CDATA[兄弟，努力吧。我也是iphone用户，拿iphone并没有代表什么，iphone也并不是装逼之用，用来装逼也很掉价，不过用户体验确实比安卓的好些。萝卜青菜各有所爱。]]></text>
        <time><![CDATA[2012-03-15 07:08:02]]></time>
    </status>

    <status>
        <text><![CDATA[耳朵耳朵你看到了马]]></text>
        <time><![CDATA[2012-03-15 07:03:00]]></time>
    </status>

    <status>
        <text><![CDATA[当在餐厅吃饭排队时，前面的人都拿出iPhone时，我嚼着9200也不错。]]></text>
        <time><![CDATA[2012-03-15 06:50:01]]></time>
    </status>

    <status>
        <text><![CDATA[结论没错，但论据很奇怪，为什么说到苹果就是装逼而不是用户体验之类，吃不到葡萄说葡萄酸的感觉，努力挣钱把。]]></text>
        <time><![CDATA[2012-03-15 06:45:01]]></time>
    </status>

    <status>
        <text><![CDATA[求问，郭小四究竟多高？]]></text>
        <time><![CDATA[2012-03-15 06:27:02]]></time>
    </status>

    <status>
        <text><![CDATA[不买就不买呗，这又不是什么大事。不买还能没了妹子？丢了工作？]]></text>
        <time><![CDATA[2012-03-15 06:25:01]]></time>
    </status>

    <status>
        <text><![CDATA[我来自一个三线城市，爸妈的工资两个人合起来才3k一个月，我还有个妹妹在读高中。即使有钱，我也舍不得买苹果的产品，对于我们家来说那些都是奢侈品。而且我也不需要那些东西来装逼，即使装了又怎样，装了还是穷。父母穷了半辈子把我拉扯大，我不能成为一个败家的儿子。]]></text>
        <time><![CDATA[2012-03-15 06:21:02]]></time>
    </status>

    <status>
        <text><![CDATA[bft.cn居然没有备案也被关闭了……]]></text>
        <time><![CDATA[2012-03-15 06:18:02]]></time>
    </status>

    <status>
        <text><![CDATA[你抱着我爱着我那么真实，可是我真的想要走了...]]></text>
        <time><![CDATA[2012-03-15 06:12:02]]></time>
    </status>

    <status>
        <text><![CDATA[Jasmin, I miss u.]]></text>
        <time><![CDATA[2012-03-15 04:09:02]]></time>
    </status>

    <status>
        <text><![CDATA[他说爱我爱得没那么深,我心里一阵阵地痛.他说我们不是爱情,是亲情;可为什么他要这样对我.我把整个心都交给了他,而他却只是因为感到适合才一起.我舍不得他,我该怎样才能让他爱上我?]]></text>
        <time><![CDATA[2012-03-15 03:59:02]]></time>
    </status>

    <status>
        <text><![CDATA[她怎么都不相信我，我该怎么办？]]></text>
        <time><![CDATA[2012-03-15 03:38:01]]></time>
    </status>

    <status>
        <text><![CDATA[被发好人卡了，哎，有点难过。。。]]></text>
        <time><![CDATA[2012-03-15 03:29:01]]></time>
    </status>

    <status>
        <text><![CDATA[他这几天的确表现出悔改之意 可是我的爱早就消磨得剩好少好少了 我不想心软回头害了两个人]]></text>
        <time><![CDATA[2012-03-15 03:19:01]]></time>
    </status>

    <status>
        <text><![CDATA[这几天没有你在 ，当然有些平淡孤单 、但我感谢这孤单，让我更加确定你是我缺少的那一半，完成我的那一半。不怕明天的世界，会变成怎样。每天看见你笑脸我就心安。我有你守在身旁 ，眼睛就可以勇敢。看岁月怎麽漫长，就算真海枯石烂就算已地老天荒，还相爱，就没遗憾。。。]]></text>
        <time><![CDATA[2012-03-15 01:35:01]]></time>
    </status>

    <status>
        <text><![CDATA[我女朋友十七岁 她总想让我打她屁股 而我想和她嘿咻嘿咻 怎么办才好…『我们通过sp认识的』现在树洞一天就让说一句了…真是的]]></text>
        <time><![CDATA[2012-03-15 01:14:01]]></time>
    </status>

    <status>
        <text><![CDATA[感觉自己和现在的男朋友心理年龄相差太大 然后世界有些不同 要稍稍缓和矫正 真的是要慢慢来 我喜欢慢慢来的感情 走的也慢吧 呵呵]]></text>
        <time><![CDATA[2012-03-14 23:43:01]]></time>
    </status>

    <status>
        <text><![CDATA[心情不太好啊]]></text>
        <time><![CDATA[2012-03-14 21:55:01]]></time>
    </status>

    <status>
        <text><![CDATA[Allen 我爱你！虽然我们分了手，我却从来也不曾恨过或者恼过你，相反想起你心里都是满满的甜蜜，只是以后再也不能和你在一起，让我好难过！希望你可以幸福！谢谢你给我的爱和快乐！]]></text>
        <time><![CDATA[2012-03-14 18:34:02]]></time>
    </status>

    <status>
        <text><![CDATA[记得微信女！]]></text>
        <time><![CDATA[2012-03-14 16:19:02]]></time>
    </status>

    <status>
        <text><![CDATA[想抱抱……＝＝]]></text>
        <time><![CDATA[2012-03-14 16:11:00]]></time>
    </status>

    <status>
        <text><![CDATA[树洞, 欢迎回来!  么么~]]></text>
        <time><![CDATA[2012-03-14 16:02:04]]></time>
    </status>

    <status>
        <text><![CDATA[#说个笑话#甲乙丙三人一起出游， 甲感冒了。晚上大家同睡一床， 甲睡中间。半夜，甲打了一个大喷嚏，乙丙的脸上都是甲的结晶。乙和丙：下次要通知我们。过了半个小时，甲：注意了！乙丙闻言赶紧钻到被窝里，并确定与外界没有连通。然后甲放了个屁。]]></text>
        <time><![CDATA[2012-03-14 16:02:03]]></time>
    </status>

    <status>
        <text><![CDATA[微信女，好久不见。以一个过来人的身份告诉你：向前走，一切都会好的。〖我好像有了忧郁症了。每天会伤感好多次，走到哪，干什么，都会想起他。已经分开第三个月了，都说时间是最好的良药，可是我为什么越走越难过。＃微信女 还有记得我的人吗 这段日子过得不太好＃〗]]></text>
        <time><![CDATA[2012-03-14 15:55:02]]></time>
    </status>

    <status>
        <text><![CDATA[只是无意间听到honeye我知道我想你了。]]></text>
        <time><![CDATA[2012-03-14 15:50:01]]></time>
    </status>

    <status>
        <text><![CDATA[脚踩两只船的感觉真的不好。]]></text>
        <time><![CDATA[2012-03-14 15:44:02]]></time>
    </status>

    <status>
        <text><![CDATA[看着犀叔的饭否，我感到我的内裤更紧了……]]></text>
        <time><![CDATA[2012-03-14 15:37:02]]></time>
    </status>

    <status>
        <text><![CDATA[我好像有了忧郁症了。每天会伤感好多次，走到哪，干什么，都会想起他。已经分开第三个月了，都说时间是最好的良药，可是我为什么越走越难过。＃微信女  还有记得我的人吗  这段日子过得不太好＃]]></text>
        <time><![CDATA[2012-03-14 15:33:02]]></time>
    </status>

    <status>
        <text><![CDATA[尼玛！谁讲了我的公交车笑话！是谁！]]></text>
        <time><![CDATA[2012-03-14 15:29:03]]></time>
    </status>

    <status>
        <text><![CDATA[爸妈要离婚。不知道该怎么办。妈妈整天找别扭，气的爸爸血压血糖都高了。可爸爸什么也没做啊。不知道为什么。爸爸打电话给我，委屈得都哭了。其实听到这消息我不惊讶，之前爸爸给我说过一次。知道他们感情已经有些问题，我也感觉得出来，但没想到这么严重。]]></text>
        <time><![CDATA[2012-03-14 15:24:02]]></time>
    </status>

    <status>
        <text><![CDATA[把生活费花光了，考试费也花了一半…]]></text>
        <time><![CDATA[2012-03-14 15:12:03]]></time>
    </status>

    <status>
        <text><![CDATA[想呆子。想抱抱]]></text>
        <time><![CDATA[2012-03-14 15:12:02]]></time>
    </status>

    <status>
        <text><![CDATA[#说个笑话#从前有根牙签走在路上，突然间它遇到一个刺猬，于是它停下来招手说：公交车！]]></text>
        <time><![CDATA[2012-03-14 15:04:02]]></time>
    </status>

    <status>
        <text><![CDATA[真心求助：介绍几本书，类似辛夷坞那种的。谢~]]></text>
        <time><![CDATA[2012-03-14 14:56:03]]></time>
    </status>

    <status>
        <text><![CDATA[求问，近期想换工作，对简历中的自我评价这一栏感觉很头疼，请教各位达人，自评是应该写得言简意赅些还是感情色彩强些？怎样让HR第一眼就亮了？类似“性格稳重，待人热情，能吃苦耐劳”是不是可以不写？跪谢！]]></text>
        <time><![CDATA[2012-03-14 14:56:02]]></time>
    </status>

    <status>
        <text><![CDATA[一切有为法,如梦幻泡影,如露亦如电,应作如是观.]]></text>
        <time><![CDATA[2012-03-14 14:50:02]]></time>
    </status>

    <status>
        <text><![CDATA[女，研究生，到了晚上会寂寞到想男人……怎么办？？？]]></text>
        <time><![CDATA[2012-03-14 14:47:02]]></time>
    </status>

    <status>
        <text><![CDATA[最寂寞的事就是写完日志没人评论 撸管后的那种空虚立刻吞噬了我]]></text>
        <time><![CDATA[2012-03-14 14:46:02]]></time>
    </status>

    <status>
        <text><![CDATA[那么多人用豆瓣，微信约炮，你们到底是怎么操作的啊！！]]></text>
        <time><![CDATA[2012-03-14 14:35:04]]></time>
    </status>

    <status>
        <text><![CDATA[树洞君我是一个女生，我对女人的身体有性幻想，现在天天想的都是女人，我是不是已经变成同性恋了？]]></text>
        <time><![CDATA[2012-03-14 14:35:02]]></time>
    </status>

    <status>
        <text><![CDATA[我的意思不是要幻想脸，而是幻想真实感。对太飘渺的对象幻想得再HIGH也不如在一个可能发生的场景上加以想象吧 转神秘树洞 没有喜欢的对象，对ex们也毫无怀念感的惨淡心境你们根本不懂，性幻想都快没有对象了啦！]]></text>
        <time><![CDATA[2012-03-14 14:34:02]]></time>
    </status>

    <status>
        <text><![CDATA[既然这样，都不想打电话了，也不想说什么，心情不好]]></text>
        <time><![CDATA[2012-03-14 14:00:03]]></time>
    </status>

    <status>
        <text><![CDATA[我今天好困啊。。。]]></text>
        <time><![CDATA[2012-03-14 13:57:00]]></time>
    </status>

    <status>
        <text><![CDATA[不会跟喜欢自己的人接触]]></text>
        <time><![CDATA[2012-03-14 13:51:02]]></time>
    </status>

    <status>
        <text><![CDATA[有没有人能给一个“会计、财务管理、企业内部控制、金融”这种类别的论文题目或者有探讨价值的问题啊~~学了一年财管神马都不知道就让我们写学年论文啊~真心不知道怎么写啊~~想了几个觉得完全凑不到五千字~~求帮助T T]]></text>
        <time><![CDATA[2012-03-14 13:32:00]]></time>
    </status>

    <status>
        <text><![CDATA[我喜欢你我喜欢你啊，每天看你饭否更新微博更新，有时候在饭否上为你喜欢的人更新饭否我心里很难受。偷偷哭了好几次，这些你都不知道，我真是没出息啊。]]></text>
        <time><![CDATA[2012-03-14 13:28:02]]></time>
    </status>

    <status>
        <text><![CDATA[想想那句感动应该和我无关的，感觉释然，更多失落。哎……]]></text>
        <time><![CDATA[2012-03-14 13:22:00]]></time>
    </status>

    <status>
        <text><![CDATA[ohno！！！2013届毕业生很惶恐，不知道做什么！！！]]></text>
        <time><![CDATA[2012-03-14 13:20:02]]></time>
    </status>

    <status>
        <text><![CDATA[今天开始接触一些机密政府信息，我这种大嘴巴，不是要把我憋死哇]]></text>
        <time><![CDATA[2012-03-14 13:16:01]]></time>
    </status>

    <status>
        <text><![CDATA[没有喜欢的对象，对ex们也毫无怀念感的惨淡心境你们根本不懂，性幻想都快没有对象了啦！]]></text>
        <time><![CDATA[2012-03-14 13:03:02]]></time>
    </status>

    <status>
        <text><![CDATA[树洞。我初中的闺蜜抢了我喜欢的男生。那个男生跟我一起旅行过，我们一起经历过很多。他拉过我的手，他kiss过我。他抱过我。我们甚至睡过一张床。我们有很多回忆。她曾经对我说，他们不可能。可是他们在一起的时候却没有告诉我。他们瞒了我好久。很难过。]]></text>
        <time><![CDATA[2012-03-14 13:02:02]]></time>
    </status>

    <status>
        <text><![CDATA[【你对刑诉法修改的愤怒，究竟有多廉价？】人民网这种正经的媒体，都使用错误版本的刑诉法修正73条规定，无怪于人民反对声浪如此大！目前提请审议的条文，明明规定，任何罪行只要指定监视居住，除无法通知外都都要在24小时内通知家属。希望大家独立思考。]]></text>
        <time><![CDATA[2012-03-14 12:47:02]]></time>
    </status>

    <status>
        <text><![CDATA[哈哈，想你了宝贝，别忘了好嘛？]]></text>
        <time><![CDATA[2012-03-14 12:46:00]]></time>
    </status>

    <status>
        <text><![CDATA[我今天在食堂吃饭的时候忘记给钱了，老板娘也忙忘记了，刚想起来，好罪过]]></text>
        <time><![CDATA[2012-03-14 12:33:02]]></time>
    </status>

    <status>
        <text><![CDATA[每天只有一条，大家会用来日记，吐槽，还是勾搭呢？求助就不用了吧～]]></text>
        <time><![CDATA[2012-03-14 12:30:02]]></time>
    </status>
</timelime>