<?xml version="1.0" encoding="UTF-8"?>
<timelime id="treeholes">
    <status>
        <text><![CDATA[我爱你]]></text>
        <time><![CDATA[2011-09-28 17:27:02]]></time>
    </status>

    <status>
        <text><![CDATA[一吵架我就异常活跃！！为什么啊！！我脑子有毛病是吧~]]></text>
        <time><![CDATA[2011-09-28 17:27:00]]></time>
    </status>

    <status>
        <text><![CDATA[那帝都人的优越感就是他们会讲京片子以及京片子~]]></text>
        <time><![CDATA[2011-09-28 17:19:01]]></time>
    </status>

    <status>
        <text><![CDATA[各位听我一言，都去睡吧，乖~]]></text>
        <time><![CDATA[2011-09-28 17:16:01]]></time>
    </status>

    <status>
        <text><![CDATA[广东人的优越感来自于他们同时会讲粤语与国语的特殊体质。]]></text>
        <time><![CDATA[2011-09-28 17:12:01]]></time>
    </status>

    <status>
        <text><![CDATA[你怎么不主动联系我  转@今天再不联系的话，我就必须得想清楚十一我怎么整了。]]></text>
        <time><![CDATA[2011-09-28 17:06:00]]></time>
    </status>

    <status>
        <text><![CDATA[今天再不联系的话，我就必须得想清楚十一我怎么整了。]]></text>
        <time><![CDATA[2011-09-28 17:03:02]]></time>
    </status>

    <status>
        <text><![CDATA[姑娘让你买东西，还好啦。记得有段时间我爱搞少妇和比我大七八岁的熟女，这些破鞋居然也暗示明示要我买东西，所以说有些女人天生就是娼妓，我能做的是玩过就甩。转@神秘树洞姑娘还没见面就暗示我陪他逛街给他买东西，这可以理解为姑娘要约炮吧？]]></text>
        <time><![CDATA[2011-09-28 16:36:01]]></time>
    </status>

    <status>
        <text><![CDATA[和妹子去看了&lt;白蛇传奇&gt;,一路笑过来可妹子听到最后一句哭了....&quot;我或许永远也无法像姐姐那样去爱一个人&quot;...妹子~你想告诉我什么呢?]]></text>
        <time><![CDATA[2011-09-28 16:24:02]]></time>
    </status>

    <status>
        <text><![CDATA[求一肤白貌美气质佳的妹纸@恋爱酱。话说妹纸才是永恒的主题。]]></text>
        <time><![CDATA[2011-09-28 16:07:02]]></time>
    </status>

    <status>
        <text><![CDATA[最简单的方法，看你能不能给对方留言板留言。@神秘树洞有人知道豆瓣怎么查询谁取消关注了我么？]]></text>
        <time><![CDATA[2011-09-28 15:57:01]]></time>
    </status>

    <status>
        <text><![CDATA[连炮友都找不到= =]]></text>
        <time><![CDATA[2011-09-28 15:25:01]]></time>
    </status>

    <status>
        <text><![CDATA[买不到火车票 联系到一张转让的 明天要去取 可是他的票价跟网上的票价信息不符合 会是假票么]]></text>
        <time><![CDATA[2011-09-28 15:22:02]]></time>
    </status>

    <status>
        <text><![CDATA[不要计较过去得失的多少。那你做好和我平淡，幸福，温馨的生活了吗？小情人？就算八十岁，我也要每天都说我爱你。]]></text>
        <time><![CDATA[2011-09-28 15:22:01]]></time>
    </status>

    <status>
        <text><![CDATA[我喜欢一个gay好久了，现在我们是闺蜜，他都不知道。]]></text>
        <time><![CDATA[2011-09-28 15:17:03]]></time>
    </status>

    <status>
        <text><![CDATA[快沉迷在电脑里。。。不要想别的！暴食全家死啊！    转@我好饿！快鼓励我安抚我教导我制止我下床找吃的！]]></text>
        <time><![CDATA[2011-09-28 15:06:03]]></time>
    </status>

    <status>
        <text><![CDATA[如果你没跟那个我看不上眼的女人暧昧来暧昧去的话，我也不至于这么绝情。]]></text>
        <time><![CDATA[2011-09-28 15:03:01]]></time>
    </status>

    <status>
        <text><![CDATA[我好饿！快鼓励我安抚我教导我制止我下床找吃的！！！]]></text>
        <time><![CDATA[2011-09-28 15:00:01]]></time>
    </status>

    <status>
        <text><![CDATA[明天又要回英国了，没有人祝福，又要开始苦逼的一年唉。。。。。。]]></text>
        <time><![CDATA[2011-09-28 14:56:05]]></time>
    </status>

    <status>
        <text><![CDATA[蜜桃成熟时]]></text>
        <time><![CDATA[2011-09-28 14:55:00]]></time>
    </status>

    <status>
        <text><![CDATA[闻香识女人]]></text>
        <time><![CDATA[2011-09-28 14:54:01]]></time>
    </status>

    <status>
        <text><![CDATA[建党伟业]]></text>
        <time><![CDATA[2011-09-28 14:48:13]]></time>
    </status>

    <status>
        <text><![CDATA[@   色戒、]]></text>
        <time><![CDATA[2011-09-28 14:48:09]]></time>
    </status>

    <status>
        <text><![CDATA[伟大的树洞，求推荐一部色香味俱全的电影，关键还是要有深度。跪求！！！]]></text>
        <time><![CDATA[2011-09-28 14:47:05]]></time>
    </status>

    <status>
        <text><![CDATA[@L.T   我，只在做一件事的时候才会想你，那就是呼吸  @焚蛋]]></text>
        <time><![CDATA[2011-09-28 14:42:02]]></time>
    </status>

    <status>
        <text><![CDATA[寂寞]]></text>
        <time><![CDATA[2011-09-28 14:39:01]]></time>
    </status>

    <status>
        <text><![CDATA[+1 @神秘树洞有些男人，你对他不好，就说你对他没那个心；对他好一点，他就翘起尾巴来，说你在发骚。说得好听叫难伺候，说得难听点就叫犯贱。死贱男人。]]></text>
        <time><![CDATA[2011-09-28 14:33:02]]></time>
    </status>

    <status>
        <text><![CDATA[不告诉你~转@神秘树洞你这是什么意思]]></text>
        <time><![CDATA[2011-09-28 14:30:03]]></time>
    </status>

    <status>
        <text><![CDATA[没什么意思]]></text>
        <time><![CDATA[2011-09-28 14:29:03]]></time>
    </status>

    <status>
        <text><![CDATA[你这是什么意思]]></text>
        <time><![CDATA[2011-09-28 14:28:02]]></time>
    </status>

    <status>
        <text><![CDATA[有些男人，你对他不好，就说你对他没那个心；对他好一点，他就翘起尾巴来，说你在发骚。说得好听叫难伺候，说得难听点就叫犯贱。死贱男人。]]></text>
        <time><![CDATA[2011-09-28 14:24:00]]></time>
    </status>

    <status>
        <text><![CDATA[有人知道豆瓣怎么查询谁取消关注了我么？]]></text>
        <time><![CDATA[2011-09-28 14:13:02]]></time>
    </status>

    <status>
        <text><![CDATA[擦你大爷，给劳资去黑人人网啊，黑你妹的人人影视啊！]]></text>
        <time><![CDATA[2011-09-28 13:47:02]]></time>
    </status>

    <status>
        <text><![CDATA[我是盐，我喜欢大脸。很喜欢很喜欢的那种喜欢。我想告诉你，我的那种喜欢是可以让我去为了和你在一起很久而付出很多努力的很有责任心的喜欢。]]></text>
        <time><![CDATA[2011-09-28 13:46:00]]></time>
    </status>

    <status>
        <text><![CDATA[这是援助交际吧 转@神秘树洞姑娘还没见面就暗示我陪他逛街给他买东西，这可以理解为姑娘要约炮吧？]]></text>
        <time><![CDATA[2011-09-28 13:44:02]]></time>
    </status>

    <status>
        <text><![CDATA[人人影视是被黑了吗？]]></text>
        <time><![CDATA[2011-09-28 13:41:03]]></time>
    </status>

    <status>
        <text><![CDATA[你本来就是傻逼 转@干物猫我还傻逼一样一直刷新人人影视的首页]]></text>
        <time><![CDATA[2011-09-28 13:40:03]]></time>
    </status>

    <status>
        <text><![CDATA[你想连窝端吗？亲]]></text>
        <time><![CDATA[2011-09-28 13:40:01]]></time>
    </status>

    <status>
        <text><![CDATA[为什么我对于喜欢的人往往想说草尼玛而不是我爱你？这是病嘛？]]></text>
        <time><![CDATA[2011-09-28 13:34:03]]></time>
    </status>

    <status>
        <text><![CDATA[拉到吧你，别自作多情了，人姑娘纯粹就是为了想让你给她买东西。。哈哈。。转@神秘树洞姑娘还没见面就暗示我陪他逛街给他买东西，这可以理解为姑娘要约炮吧？]]></text>
        <time><![CDATA[2011-09-28 13:33:12]]></time>
    </status>

    <status>
        <text><![CDATA[Bingo!转@神秘树洞姑娘还没见面就暗示我陪他逛街给他买东西，这可以理解为姑娘要约炮吧？]]></text>
        <time><![CDATA[2011-09-28 13:23:02]]></time>
    </status>

    <status>
        <text><![CDATA[自己注册个马甲试去～转@神秘树洞关注@饭_安佛转请问大家，拉黑以及删除关注我的人对方会收到通知吗？]]></text>
        <time><![CDATA[2011-09-28 13:21:02]]></time>
    </status>

    <status>
        <text><![CDATA[除非他是个关注了 @饭_安佛的二货 转@神秘树洞请问大家，拉黑以及删除关注我的人对方会收到通知吗？]]></text>
        <time><![CDATA[2011-09-28 13:21:00]]></time>
    </status>

    <status>
        <text><![CDATA[姑娘还没见面就暗示我陪他逛街给他买东西，这可以理解为姑娘要约炮吧？]]></text>
        <time><![CDATA[2011-09-28 13:19:00]]></time>
    </status>

    <status>
        <text><![CDATA[关注@饭_安佛转请问大家，拉黑以及删除关注我的人对方会收到通知吗？]]></text>
        <time><![CDATA[2011-09-28 13:14:00]]></time>
    </status>

    <status>
        <text><![CDATA[请问大家，拉黑以及删除关注我的人对方会收到通知吗？ //不会的]]></text>
        <time><![CDATA[2011-09-28 13:11:03]]></time>
    </status>

    <status>
        <text><![CDATA[不会~ @神秘树洞请问大家，拉黑以及删除关注我的人对方会收到通知吗？]]></text>
        <time><![CDATA[2011-09-28 13:11:02]]></time>
    </status>

    <status>
        <text><![CDATA[请问大家，拉黑以及删除关注我的人对方会收到通知吗？]]></text>
        <time><![CDATA[2011-09-28 13:09:04]]></time>
    </status>

    <status>
        <text><![CDATA[对外汉语专业貌似不考高数吧 @神秘树洞大三 对外汉语专业 第一外语西语 没学过高数 是考研还是不考研?跨专业么?]]></text>
        <time><![CDATA[2011-09-28 13:09:04]]></time>
    </status>

    <status>
        <text><![CDATA[大三 对外汉语专业 第一外语西语 没学过高数 是考研还是不考研?跨专业么?]]></text>
        <time><![CDATA[2011-09-28 12:33:01]]></time>
    </status>

    <status>
        <text><![CDATA[我觉得其实要不是还没谈过恋爱 可以考虑和你做炮友的 你们说 这个算爱情嘛？]]></text>
        <time><![CDATA[2011-09-28 12:28:00]]></time>
    </status>

    <status>
        <text><![CDATA[这种情况只能说明你今天才在下的毛片你的室友昨晚已经偷偷用迅雷下好了. 转@神秘树洞电信八兆的宽带，四个人用，最高迅雷下载速度9000KB＼S，平均500＋算快吗？]]></text>
        <time><![CDATA[2011-09-28 12:09:01]]></time>
    </status>

    <status>
        <text><![CDATA[看平均速度还是可以的 @神秘树洞迅雷告诉你的峰值速度能信的吗....]]></text>
        <time><![CDATA[2011-09-28 12:08:03]]></time>
    </status>

    <status>
        <text><![CDATA[靠，今晚网速不稳定，刚才这把三国杀差点就拖后腿了。]]></text>
        <time><![CDATA[2011-09-28 12:08:03]]></time>
    </status>

    <status>
        <text><![CDATA[4个公网IP吗？@神秘树洞我们也是8M宽带，4个人用，平均1M/s，最快2M。你弱爆了。转@神秘树洞电信八兆的宽带，四个人用，最高迅雷下载速度9000KB＼S，平均500＋算快吗？]]></text>
        <time><![CDATA[2011-09-28 12:08:03]]></time>
    </status>

    <status>
        <text><![CDATA[可惜的是我仍在天朝，迅雷最高下载速度是900，打错了。]]></text>
        <time><![CDATA[2011-09-28 12:08:02]]></time>
    </status>

    <status>
        <text><![CDATA[我想问你三个问题。1 你是在吊我胃口嘛？2 你还是想和我玩玩呢？3 我如果喜欢你的话，你会喜欢我吗？]]></text>
        <time><![CDATA[2011-09-28 12:05:02]]></time>
    </status>

    <status>
        <text><![CDATA[迅雷告诉你的峰值速度能信的吗....  转@神秘树洞四川电信FTTH 8M测试只有800K你能用到9000K的，你不在兲朝@神秘树洞电信八兆的宽带，四个人用，最高迅雷下载速度9000KB＼S，平均500＋算快吗？]]></text>
        <time><![CDATA[2011-09-28 12:05:01]]></time>
    </status>

    <status>
        <text><![CDATA[我们也是8M宽带，4个人用，平均1M/s，最快2M。你弱爆了。转@神秘树洞电信八兆的宽带，四个人用，最高迅雷下载速度9000KB＼S，平均500＋算快吗？]]></text>
        <time><![CDATA[2011-09-28 12:03:01]]></time>
    </status>

    <status>
        <text><![CDATA[@恋爱酱是臭傻逼！]]></text>
        <time><![CDATA[2011-09-28 12:01:04]]></time>
    </status>

    <status>
        <text><![CDATA[我是楼主，操好了也走人了，长头发到处都是才用吸尘器搞好，麻烦！这个菜头痴的傻的，这都要感恩，我还感恩的过来？转@和菜头女性比男性少几百万，有个炮友，难道不应该感恩吗？尼玛！太粗俗了，就不懂要怀着一颗感恩的心吗？ 转@神秘树洞过半小时她要来，就要操逼了，我不喜欢她，只想操一操]]></text>
        <time><![CDATA[2011-09-28 12:01:02]]></time>
    </status>

    <status>
        <text><![CDATA[四川电信FTTH 8M测试只有800K你能用到9000K的，你不在兲朝@神秘树洞电信八兆的宽带，四个人用，最高迅雷下载速度9000KB＼S，平均500＋算快吗？]]></text>
        <time><![CDATA[2011-09-28 12:01:03]]></time>
    </status>

    <status>
        <text><![CDATA[电信八兆的宽带，四个人用，最高迅雷下载速度9000KB＼S，平均500＋算快吗？]]></text>
        <time><![CDATA[2011-09-28 11:58:01]]></time>
    </status>

    <status>
        <text><![CDATA[据国外媒体报道，来自“迷你微软”（Mini-Microsoft）博客网站的报道称，微软首席执行官史蒂夫·鲍尔默（Steve Ballmer）已不再受到微软员工的拥护。在最近举行的微软公司年会中，当鲍尔默演讲时“成群结伙”的微软员工纷纷离开了会场。]]></text>
        <time><![CDATA[2011-09-28 11:32:01]]></time>
    </status>

    <status>
        <text><![CDATA[If only one active call exists on the directory number, the first invocation of a feature results in putting the active call on hold and ini]]></text>
        <time><![CDATA[2011-09-28 11:28:02]]></time>
    </status>

    <status>
        <text><![CDATA[test]]></text>
        <time><![CDATA[2011-09-28 11:26:04]]></time>
    </status>

    <status>
        <text><![CDATA[会调课的，SB]]></text>
        <time><![CDATA[2011-09-28 11:24:02]]></time>
    </status>

    <status>
        <text><![CDATA[桂花开了，石榴熟了。]]></text>
        <time><![CDATA[2011-09-28 11:22:04]]></time>
    </status>

    <status>
        <text><![CDATA[鄙视你，资本主义一天都不放假。。因为国庆是周六。。转@神秘树洞周六开始十一，放七天后又是周六。八九号学校的安排是：照正常教学秩序。意思是，周末没课继续放假。放九天的大学生你伤不起啊哈哈哈。]]></text>
        <time><![CDATA[2011-09-28 11:22:02]]></time>
    </status>

    <status>
        <text><![CDATA[周六开始十一，放七天后又是周六。八九号学校的安排是：照正常教学秩序。意思是，周末没课继续放假。放九天的大学生你伤不起啊哈哈哈。]]></text>
        <time><![CDATA[2011-09-28 11:18:03]]></time>
    </status>

    <status>
        <text><![CDATA[爱理不理？你就爱理不理吧你！可是劳资就是悲催地想你…╯_╰]]></text>
        <time><![CDATA[2011-09-28 11:12:01]]></time>
    </status>

    <status>
        <text><![CDATA[换个季节，换个心情，同时 哥自然也要换个男朋友]]></text>
        <time><![CDATA[2011-09-28 10:55:01]]></time>
    </status>

    <status>
        <text><![CDATA[和菜头的树洞可好，但就是不敢写]]></text>
        <time><![CDATA[2011-09-28 10:37:01]]></time>
    </status>

    <status>
        <text><![CDATA[好想给树洞写信，但是又心烦]]></text>
        <time><![CDATA[2011-09-28 10:35:02]]></time>
    </status>

    <status>
        <text><![CDATA[你妹啊树洞都很紧吗]]></text>
        <time><![CDATA[2011-09-28 10:27:01]]></time>
    </status>

    <status>
        <text><![CDATA[会高潮!]]></text>
        <time><![CDATA[2011-09-28 10:25:00]]></time>
    </status>

    <status>
        <text><![CDATA[我在看大学宿舍用的小洗衣机，谁能帮个忙推荐个——@十年君]]></text>
        <time><![CDATA[2011-09-28 10:24:01]]></time>
    </status>

    <status>
        <text><![CDATA[如果同一个时间无数人给树洞发，会怎么样？]]></text>
        <time><![CDATA[2011-09-28 10:23:00]]></time>
    </status>

    <status>
        <text><![CDATA[树洞好有趣]]></text>
        <time><![CDATA[2011-09-28 10:20:01]]></time>
    </status>

    <status>
        <text><![CDATA[不知道他想不想我,反正我俩没有联系了!]]></text>
        <time><![CDATA[2011-09-28 10:19:01]]></time>
    </status>

    <status>
        <text><![CDATA[我不能在想念里度日。看书去咯。]]></text>
        <time><![CDATA[2011-09-28 10:17:02]]></time>
    </status>

    <status>
        <text><![CDATA[他不想你。转@神秘树洞我最近时常想念我的饭否419小基友。]]></text>
        <time><![CDATA[2011-09-28 10:11:00]]></time>
    </status>

    <status>
        <text><![CDATA[我最近时常想念我的饭否419小基友。]]></text>
        <time><![CDATA[2011-09-28 10:09:01]]></time>
    </status>

    <status>
        <text><![CDATA[妹子，上吧 转@神秘树洞有个男孩纸，我们只有在学校的群里说过话，在群聚的时候敬过一杯酒，但是他的兄弟们都说他特别喜欢我，说他很害羞。饭否众快帮我分析分析哇~]]></text>
        <time><![CDATA[2011-09-28 10:04:02]]></time>
    </status>

    <status>
        <text><![CDATA[他是受，你要主动]]></text>
        <time><![CDATA[2011-09-28 10:03:00]]></time>
    </status>

    <status>
        <text><![CDATA[有个男孩纸，我们只有在学校的群里说过话，在群聚的时候敬过一杯酒，但是他的兄弟们都说他特别喜欢我，说他很害羞。饭否众快帮我分析分析哇~]]></text>
        <time><![CDATA[2011-09-28 10:00:01]]></time>
    </status>

    <status>
        <text><![CDATA[炮友，也要珍惜。装逼，有一天也会被艹的！转@神秘树洞操人老婆者，妻女被人操 转@神秘树洞过半小时她要来，就要操逼了，我不喜欢她，只想操一操]]></text>
        <time><![CDATA[2011-09-28 09:55:00]]></time>
    </status>

    <status>
        <text><![CDATA[你们的饭友都是随便看看里认识的吗~]]></text>
        <time><![CDATA[2011-09-28 09:50:02]]></time>
    </status>

    <status>
        <text><![CDATA[可是我们根本没在一起啊！他告诉他爸妈告诉我姐说喜欢我然后聊了一阵就没下文了，倒霉催的我还真的对他有好感了 转@神秘树洞分了吧 没意思的！！！ @神秘树洞你是世界上的另一个我么 转@神秘树洞树洞君 如果口口声声说喜欢你的人半个月没理你了 还要继续么]]></text>
        <time><![CDATA[2011-09-28 09:48:02]]></time>
    </status>

    <status>
        <text><![CDATA[我想下班啊 怎么最近这么懒啊 做事情这么拖啊....  哦咪头佛]]></text>
        <time><![CDATA[2011-09-28 09:37:01]]></time>
    </status>

    <status>
        <text><![CDATA[我还是喜欢他，但是大姐说，那种喜欢已经不是喜欢了~~那就让它化为尘世的美好。愿你开开心心地忘记我]]></text>
        <time><![CDATA[2011-09-28 09:21:01]]></time>
    </status>

    <status>
        <text><![CDATA[半小时我就要去上课了，可以上课了，我不喜欢上课，借教室泡空调。]]></text>
        <time><![CDATA[2011-09-28 09:18:01]]></time>
    </status>

    <status>
        <text><![CDATA[半小时我就要去找他了，可以操逼了，我不喜欢他，借管操一操。]]></text>
        <time><![CDATA[2011-09-28 09:15:02]]></time>
    </status>

    <status>
        <text><![CDATA[操人老婆者，妻女被人操 转@神秘树洞过半小时她要来，就要操逼了，我不喜欢她，只想操一操]]></text>
        <time><![CDATA[2011-09-28 09:13:02]]></time>
    </status>

    <status>
        <text><![CDATA[过半小时她要来，就要操逼了，我不喜欢她，只想操一操]]></text>
        <time><![CDATA[2011-09-28 09:08:01]]></time>
    </status>

    <status>
        <text><![CDATA[恩，我一直以为自己是粪蛋，最后她跟别人跑的时候对我说，其实你是好人转@神秘树洞为什么总在分手的时候，我才发现她原来那么的爱我呢？她哭着说，我从未顾及过她的感受，她说的每一句话我听着都那么痛。她说，你只是在我身上实现自己的梦。恋爱的梦。听着，那么痛。我原来，也是一个混蛋。]]></text>
        <time><![CDATA[2011-09-28 08:07:01]]></time>
    </status>

    <status>
        <text><![CDATA[分了吧 没意思的！！！ @神秘树洞你是世界上的另一个我么 转@神秘树洞树洞君 如果口口声声说喜欢你的人半个月没理你了 还要继续么]]></text>
        <time><![CDATA[2011-09-28 07:46:03]]></time>
    </status>

    <status>
        <text><![CDATA[好吧，其实我也有段时间没怎么联系喜欢的人了，一个多月前表白被发卡。]]></text>
        <time><![CDATA[2011-09-28 07:46:01]]></time>
    </status>

    <status>
        <text><![CDATA[大约是的吧 那你是怎么采取措施的 给你的另一个我参考下 转@神秘树洞你是世界上的另一个我么 转@神秘树洞树洞君 如果口口声声说喜欢你的人半个月没理你了 还要继续么]]></text>
        <time><![CDATA[2011-09-28 07:45:02]]></time>
    </status>

    <status>
        <text><![CDATA[你是世界上的另一个我么 转@神秘树洞树洞君 如果口口声声说喜欢你的人半个月没理你了 还要继续么]]></text>
        <time><![CDATA[2011-09-28 07:42:02]]></time>
    </status>
</timelime>