<?xml version="1.0" encoding="UTF-8"?>
<timelime id="treeholes">
    <status>
        <text><![CDATA[告诉你个真相，在乎处的男人都是傻逼，神秘树洞男人为什么这么在意处？自己不是就不要要求别人好不好？？…！]]></text>
        <time><![CDATA[2011-04-09 16:10:02]]></time>
    </status>

    <status>
        <text><![CDATA[有处女情节的男人大部分都是不自信的男人，迂起来特迂，怂起来特怂。]]></text>
        <time><![CDATA[2011-04-09 16:10:01]]></time>
    </status>

    <status>
        <text><![CDATA[其实每个人都有处女情结的嘛，就好像去吃饭，有用过的筷子跟没掰开的一次性筷子，你选哪个？ 转@神秘树洞男人为什么这么在意处？自己不是就不要要求别人好不好？？…！]]></text>
        <time><![CDATA[2011-04-09 16:09:01]]></time>
    </status>

    <status>
        <text><![CDATA[男人为什么这么在意处？自己不是就不要要求别人好不好？？…！]]></text>
        <time><![CDATA[2011-04-09 16:05:01]]></time>
    </status>

    <status>
        <text><![CDATA[我真是看见处女情结就生气。。去做一个你的处女迪克又能分辨吗？！。。]]></text>
        <time><![CDATA[2011-04-09 16:04:01]]></time>
    </status>

    <status>
        <text><![CDATA[敢问发上一条的同学，你爱的是她还是她的处女膜？她如果不是处女了，你的爱会打折扣吗？]]></text>
        <time><![CDATA[2011-04-09 16:02:01]]></time>
    </status>

    <status>
        <text><![CDATA[希望在我事业有成的时候，你未嫁，我未娶，你还是处女，我一定要你做我的新娘！]]></text>
        <time><![CDATA[2011-04-09 16:00:01]]></time>
    </status>

    <status>
        <text><![CDATA[很窘的喜欢你了,可是你应该感觉不到吧...算了吧反正也不可能有什么未来.我就是寂寞太久了吧.]]></text>
        <time><![CDATA[2011-04-09 15:42:02]]></time>
    </status>

    <status>
        <text><![CDATA[@躺糖都瘦了..........我们完了...........分手吧...]]></text>
        <time><![CDATA[2011-04-09 15:39:01]]></time>
    </status>

    <status>
        <text><![CDATA[我想看看树洞靠谱不？！]]></text>
        <time><![CDATA[2011-04-09 15:28:02]]></time>
    </status>

    <status>
        <text><![CDATA[啊]]></text>
        <time><![CDATA[2011-04-09 15:03:07]]></time>
    </status>

    <status>
        <text><![CDATA[药家鑫该死，斩立决。无论多少无良者为他开脱，杀无赦。鉴定完毕！]]></text>
        <time><![CDATA[2011-04-09 14:58:01]]></time>
    </status>

    <status>
        <text><![CDATA[你没谈过八，男朋友可以给你带来很多朋友给你不了的各种温暖。转@神秘树洞不知道朋友和男朋友的区别在哪里？就是可以做糟糕的事情吗？]]></text>
        <time><![CDATA[2011-04-09 14:21:02]]></time>
    </status>

    <status>
        <text><![CDATA[不知道朋友和男朋友的区别在哪里？就是可以做糟糕的事情吗？]]></text>
        <time><![CDATA[2011-04-09 14:16:01]]></time>
    </status>

    <status>
        <text><![CDATA[我喜欢你。]]></text>
        <time><![CDATA[2011-04-09 14:15:01]]></time>
    </status>

    <status>
        <text><![CDATA[试试这个洞好不好用]]></text>
        <time><![CDATA[2011-04-09 14:14:01]]></time>
    </status>

    <status>
        <text><![CDATA[树洞。我爱他，可是他不会回我消息，我不知道怎么办，，难道真的要慢慢冷淡下去么？]]></text>
        <time><![CDATA[2011-04-09 14:11:03]]></time>
    </status>

    <status>
        <text><![CDATA[我快變態了]]></text>
        <time><![CDATA[2011-04-09 14:06:01]]></time>
    </status>

    <status>
        <text><![CDATA[好久不来树洞叨逼了。洞洞你猜我是谁？]]></text>
        <time><![CDATA[2011-04-09 14:04:01]]></time>
    </status>

    <status>
        <text><![CDATA[好吧，我的学生，你就随便顶撞吧，不管怎么样，你都是我的学生啊。]]></text>
        <time><![CDATA[2011-04-09 14:01:01]]></time>
    </status>

    <status>
        <text><![CDATA[不能够，徒弟顶撞师傅是爱的教育，师傅教训徒弟是绝对不许。]]></text>
        <time><![CDATA[2011-04-09 13:57:01]]></time>
    </status>

    <status>
        <text><![CDATA[学生顶撞老师，就得被说是对老师进行人格污辱;老师公然羞辱学生，就可以说成是良药苦口爱的教育??]]></text>
        <time><![CDATA[2011-04-09 13:49:02]]></time>
    </status>

    <status>
        <text><![CDATA[徒弟，你是师傅的，为师会一辈子照顾你的，并且教你武功。满足你杀掉我的愿望，虽然这需要很久，直到你学会库库齐齐卡汽车人变形的那一天。]]></text>
        <time><![CDATA[2011-04-09 13:43:01]]></time>
    </status>

    <status>
        <text><![CDATA[服务——WlAN Auto Config（启动~）]]></text>
        <time><![CDATA[2011-04-09 13:36:01]]></time>
    </status>

    <status>
        <text><![CDATA[Windows 无法自动将 IP 协议堆栈绑定到网络适配器，怎么解决？]]></text>
        <time><![CDATA[2011-04-09 13:34:02]]></time>
    </status>

    <status>
        <text><![CDATA[如果···是我···是我的话···不管他是男的或女的···是猫狗也好···植物也好···机器也好我一定都会把他找出来，然后绝对会···喜欢上他。西西，为了你，我愿意。]]></text>
        <time><![CDATA[2011-04-09 13:31:01]]></time>
    </status>

    <status>
        <text><![CDATA[不想再上饭否了。时间长了，感到厌倦了......没有什么是离不开的，对吧？]]></text>
        <time><![CDATA[2011-04-09 13:29:02]]></time>
    </status>

    <status>
        <text><![CDATA[北鼻来北鼻去的，北鼻要生日了！]]></text>
        <time><![CDATA[2011-04-09 13:29:01]]></time>
    </status>

    <status>
        <text><![CDATA[北鼻，十年一刀，我能当你男人了吗？]]></text>
        <time><![CDATA[2011-04-09 13:26:01]]></time>
    </status>

    <status>
        <text><![CDATA[北鼻，你跟我一起拍的合照里边你好阳光好开心哦，可是你走之后看到你一个人的照片好孤单好忧伤好可怜哦，耷拉着的嘴好想把它拉出微笑的弧度，北鼻不管有多远我们最后都会一起的好吗]]></text>
        <time><![CDATA[2011-04-09 13:18:01]]></time>
    </status>

    <status>
        <text><![CDATA[树洞树洞，你保佑我明天的NECCS能拿个好名次吧！]]></text>
        <time><![CDATA[2011-04-09 13:03:01]]></time>
    </status>

    <status>
        <text><![CDATA[跪求除番墙外同步推特的办法。ps:番墙后又不能进饭否了。]]></text>
        <time><![CDATA[2011-04-09 12:59:02]]></time>
    </status>

    <status>
        <text><![CDATA[求，有谁做过一组网页，用到xml，js等，最好带数据库。。私信@蘇小默谢谢]]></text>
        <time><![CDATA[2011-04-09 11:27:01]]></time>
    </status>

    <status>
        <text><![CDATA[我是个想勾搭妹纸的妹纸,求勾搭....]]></text>
        <time><![CDATA[2011-04-09 11:22:01]]></time>
    </status>

    <status>
        <text><![CDATA[嗷！瓦也想要个帅大叔来爱我昂！又当爹又当妈的狠温馨狠有爱有木有！求勾引大叔攻略啊喂！]]></text>
        <time><![CDATA[2011-04-09 11:07:02]]></time>
    </status>

    <status>
        <text><![CDATA[这位饭友，我也遇到和你一样的情况，我觉得未来很迷茫，还是抓紧时间出国吧，我要去读书了。祝你我好运。@树洞啊树洞啊，出国还是恋爱？我好矛盾，选择出国就错过了一个女孩子，可是选她，我的理想就实现不了。我该怎么办？]]></text>
        <time><![CDATA[2011-04-09 11:03:01]]></time>
    </status>

    <status>
        <text><![CDATA[也才3天没见而已，现在坐在回程的车上，又想偷偷潜过去看他一眼。还是算了吧，再忍耐一个礼拜吧傻瓜。希望不要down下来。]]></text>
        <time><![CDATA[2011-04-09 10:52:01]]></time>
    </status>

    <status>
        <text><![CDATA[唉   嘛时候能掉10KJ啊啊啊 啊]]></text>
        <time><![CDATA[2011-04-09 10:26:02]]></time>
    </status>

    <status>
        <text><![CDATA[洞洞，什么电脑桌面美化软件好用，要占内存小的]]></text>
        <time><![CDATA[2011-04-09 10:02:02]]></time>
    </status>

    <status>
        <text><![CDATA[出国。今天读《炼金术士》里面说，真正的爱情不会阻止你去实现自己的天命（即梦想）。出国吧。转@神秘树洞树洞啊树洞啊，出国还是恋爱？我好矛盾，选择出国就错过了一个女孩子，可是选她，我的理想就实现不了。我该怎么办？]]></text>
        <time><![CDATA[2011-04-09 10:00:02]]></time>
    </status>

    <status>
        <text><![CDATA[cs你真是个傻逼]]></text>
        <time><![CDATA[2011-04-09 09:03:02]]></time>
    </status>

    <status>
        <text><![CDATA[想辞职]]></text>
        <time><![CDATA[2011-04-09 08:19:01]]></time>
    </status>

    <status>
        <text><![CDATA[我用了一个星期求证他的名字 别人却轻而易举的拿到他的电话 原来喜欢他的人有这么多 这下我更不敢向前了]]></text>
        <time><![CDATA[2011-04-09 08:18:01]]></time>
    </status>

    <status>
        <text><![CDATA[死孩子看书去！]]></text>
        <time><![CDATA[2011-04-09 08:09:01]]></time>
    </status>

    <status>
        <text><![CDATA[走吧走吧～不要让两个人都那么痛苦。转@神秘树洞树洞啊树洞啊，出国还是恋爱？我好矛盾，选择出国就错过了一个女孩子，可是选她，我的理想就实现不了。我该怎么办？]]></text>
        <time><![CDATA[2011-04-09 08:08:01]]></time>
    </status>

    <status>
        <text><![CDATA[去你妈的温柔只给女朋友！老娘不稀罕！哼]]></text>
        <time><![CDATA[2011-04-09 08:02:01]]></time>
    </status>

    <status>
        <text><![CDATA[从你开始犹豫的时候就说明那个女孩子在你心里不是百分百了，出国吧，不为别人做任何牺牲也别让别人为你牺牲，不然将来总有“都是因为你才毁了我”的时候。 转@神秘树洞树洞啊树洞啊，出国还是恋爱？我好矛盾，选择出国就错过了一个女孩子，可是选她，我的理想就实现不了。我该怎么办？]]></text>
        <time><![CDATA[2011-04-09 07:42:02]]></time>
    </status>

    <status>
        <text><![CDATA[出国！不要回来了！！你明白的！！！转@神秘树洞树洞啊树洞啊，出国还是恋爱？我好矛盾，选择出国就错过了一个女孩子，可是选她，我的理想就实现不了。我该怎么办？]]></text>
        <time><![CDATA[2011-04-09 07:36:02]]></time>
    </status>

    <status>
        <text><![CDATA[树洞啊树洞啊，出国还是恋爱？我好矛盾，选择出国就错过了一个女孩子，可是选她，我的理想就实现不了。我该怎么办？]]></text>
        <time><![CDATA[2011-04-09 07:33:01]]></time>
    </status>

    <status>
        <text><![CDATA[电脑运行突然自己断电，再开电源灯亮，电源cpu显卡风扇都转，硬盘灯只亮几秒，无报警，光驱有反应，拆机后发现电源有烧塑料的味道，是不是电源坏了？]]></text>
        <time><![CDATA[2011-04-09 07:04:01]]></time>
    </status>

    <status>
        <text><![CDATA[叔已经做过了。没事。]]></text>
        <time><![CDATA[2011-04-09 06:50:02]]></time>
    </status>

    <status>
        <text><![CDATA[她说庄清纯，庄无辜。庄可爱。她不姓杨。她姓庄]]></text>
        <time><![CDATA[2011-04-09 03:53:01]]></time>
    </status>

    <status>
        <text><![CDATA[杨幂长得真的好那啥，整形失败？没下巴？肥猪牛？]]></text>
        <time><![CDATA[2011-04-09 03:50:02]]></time>
    </status>

    <status>
        <text><![CDATA[思春了，树洞]]></text>
        <time><![CDATA[2011-04-09 03:37:02]]></time>
    </status>

    <status>
        <text><![CDATA[树洞树洞，我好想见他！]]></text>
        <time><![CDATA[2011-04-09 03:23:03]]></time>
    </status>

    <status>
        <text><![CDATA[杨幂长那么俗 这么多男同胞喜欢 算奇迹了吧]]></text>
        <time><![CDATA[2011-04-09 03:23:02]]></time>
    </status>

    <status>
        <text><![CDATA[我这是怎么了。如此狂热，却如此漫无目的。为什么对其他人的爱羡慕妒忌恨。为什么我总是成为最没勇气最可笑的电灯胆。为什么一切的感情只能够让自己恶狠狠的吞下去。为什么。可恶的失力感。]]></text>
        <time><![CDATA[2011-04-09 03:22:02]]></time>
    </status>

    <status>
        <text><![CDATA[真可惜，我想了很久，都没有秘密可说。]]></text>
        <time><![CDATA[2011-04-09 03:19:01]]></time>
    </status>

    <status>
        <text><![CDATA[树洞树洞，为毛我总遇见窝囊废？]]></text>
        <time><![CDATA[2011-04-09 02:59:01]]></time>
    </status>

    <status>
        <text><![CDATA[我说你丫想骂我直说好么别念经了好么，劳资听不懂啊！！！这种憋屈感你不难过么，你不难过我还难过呢！！！玛德我都不知道哪里碍着你大小姐了，拜托死也要让人死个明白好伐！！！]]></text>
        <time><![CDATA[2011-04-09 02:56:02]]></time>
    </status>

    <status>
        <text><![CDATA[爱我请举脚趾~~]]></text>
        <time><![CDATA[2011-04-09 02:19:02]]></time>
    </status>

    <status>
        <text><![CDATA[南京26岁男求异性炮友，fanfou4@gmail.com。]]></text>
        <time><![CDATA[2011-04-09 02:14:02]]></time>
    </status>

    <status>
        <text><![CDATA[南京26岁男求同性炮友，fanfou4@gmail.com。]]></text>
        <time><![CDATA[2011-04-09 02:10:01]]></time>
    </status>

    <status>
        <text><![CDATA[南京26岁男求同性炮友，fanfou4@gmail.com。]]></text>
        <time><![CDATA[2011-04-09 02:09:01]]></time>
    </status>

    <status>
        <text><![CDATA[南京26岁男求异性炮友，fanfou4@gmail.com。]]></text>
        <time><![CDATA[2011-04-09 02:07:02]]></time>
    </status>

    <status>
        <text><![CDATA[既渴望了解又害怕被了解，没有最近访客以及隐私设置的新浪微博用久了就会有这种感觉。]]></text>
        <time><![CDATA[2011-04-09 01:38:01]]></time>
    </status>

    <status>
        <text><![CDATA[亚灭碟]]></text>
        <time><![CDATA[2011-04-09 01:31:02]]></time>
    </status>

    <status>
        <text><![CDATA[插入！]]></text>
        <time><![CDATA[2011-04-09 01:30:02]]></time>
    </status>

    <status>
        <text><![CDATA[树洞，你赶紧告诉大伙儿我到底是谁，他们很想知道。]]></text>
        <time><![CDATA[2011-04-09 01:07:01]]></time>
    </status>

    <status>
        <text><![CDATA[楼下你不在乎就不会来说啦]]></text>
        <time><![CDATA[2011-04-09 00:59:02]]></time>
    </status>

    <status>
        <text><![CDATA[不理我拉倒！其实我怎么一点都不难过呢= =果然越来越麻痹了吗！]]></text>
        <time><![CDATA[2011-04-09 00:46:01]]></time>
    </status>

    <status>
        <text><![CDATA[洞洞君。你让我看到了很多人想说的东西。可是。我觉得自己想说的话还是不能诚实的在你这里说出来。有些话原来真的只能烂在肚子里。恩～背了太多秘密的人会累吧。bye~]]></text>
        <time><![CDATA[2011-04-08 19:58:02]]></time>
    </status>

    <status>
        <text><![CDATA[贫穷才最可怕。]]></text>
        <time><![CDATA[2011-04-08 19:21:02]]></time>
    </status>

    <status>
        <text><![CDATA[别去看！慢慢习惯了，有天你会发现自己看见那个人页面都懒的打开。]]></text>
        <time><![CDATA[2011-04-08 18:28:02]]></time>
    </status>

    <status>
        <text><![CDATA[正在极力控制自己不上淫淫。。真怕一忍不住爪子就点过去了。。。。哎，你们说，越是这样寂寞的时候越不能去怀念过往对吧？不然又得难过了。。]]></text>
        <time><![CDATA[2011-04-08 18:23:01]]></time>
    </status>

    <status>
        <text><![CDATA[你好。再见。如是而已，姑娘们。]]></text>
        <time><![CDATA[2011-04-08 17:14:01]]></time>
    </status>

    <status>
        <text><![CDATA[有点困惑了 磨合了很久 可是还是不行 可能真的不适合 我不能把最好的年华全耗给他]]></text>
        <time><![CDATA[2011-04-08 17:05:01]]></time>
    </status>

    <status>
        <text><![CDATA[和男友分手。互相冷淡了将近一星期，提出来的时候他倒也没说什么，挺痛快的。结果现在他各种改签名，各种痴情种。据说还逮着个人就说这事，特别是女的。额。树洞君不要鄙视我，我只是有点无奈。]]></text>
        <time><![CDATA[2011-04-08 16:58:02]]></time>
    </status>

    <status>
        <text><![CDATA[冯伊伊！你个混蛋！！]]></text>
        <time><![CDATA[2011-04-08 16:26:02]]></time>
    </status>

    <status>
        <text><![CDATA[求推荐适合给女生送的耳机！350以下，3.5毫米，入耳式，有线控最好，没有也行。事关咱终身幸福，大家务必帮个忙啊！]]></text>
        <time><![CDATA[2011-04-08 16:23:02]]></time>
    </status>

    <status>
        <text><![CDATA[我想在饭否写一个爱情小说，每天写一小点儿。感觉有点像晒恩爱，怕被人讨厌。很烦恼。王建国，你说我是写还是不写好呢。。]]></text>
        <time><![CDATA[2011-04-08 16:21:01]]></time>
    </status>

    <status>
        <text><![CDATA[小乖不会扔掉猪哼哼，也不会扔掉大乖。转@神秘树洞问：小乖为什么要扔掉猪头？]]></text>
        <time><![CDATA[2011-04-08 16:20:02]]></time>
    </status>

    <status>
        <text><![CDATA[饭否君，你一定是男生吧？我好喜欢你啊]]></text>
        <time><![CDATA[2011-04-08 16:11:01]]></time>
    </status>

    <status>
        <text><![CDATA[我后悔了，可是时间来不及。我只是个胆小鬼]]></text>
        <time><![CDATA[2011-04-08 15:59:02]]></time>
    </status>

    <status>
        <text><![CDATA[臭寶，我愛你]]></text>
        <time><![CDATA[2011-04-08 15:58:02]]></time>
    </status>

    <status>
        <text><![CDATA[（蘑菇蘑菇你不会开花，小姐小姐你还爱他吗？）（。。。嗯。）（你真没出息。）（可我乐意。）]]></text>
        <time><![CDATA[2011-04-08 15:57:01]]></time>
    </status>

    <status>
        <text><![CDATA[洞洞明天五点二十我来对你说早上好]]></text>
        <time><![CDATA[2011-04-08 15:55:02]]></time>
    </status>

    <status>
        <text><![CDATA[问：小乖为什么要扔掉猪头？]]></text>
        <time><![CDATA[2011-04-08 15:54:02]]></time>
    </status>

    <status>
        <text><![CDATA[这种冻结只是冻结网银而已～去ATM取钱完全不耽误～ 转 @神秘树洞在网页上多次换密码登陆，多次密码错误此账号就会被冻结，如果不幸试对密码就把卡上的钱捐给希望工程。。。]]></text>
        <time><![CDATA[2011-04-08 15:48:01]]></time>
    </status>

    <status>
        <text><![CDATA[在网页上多次换密码登陆，多次密码错误此账号就会被冻结，如果不幸试对密码就把卡上的钱捐给希望工程。。。转@神秘树洞收一短信【农行6228481190550642118唐璐  +8613030038614】，我要怎弄？？？]]></text>
        <time><![CDATA[2011-04-08 15:07:01]]></time>
    </status>

    <status>
        <text><![CDATA[今天刷机没人品。没技术。去墙角种蘑菇，画圈圈，不管三七二十一，诅咒。]]></text>
        <time><![CDATA[2011-04-08 15:06:03]]></time>
    </status>

    <status>
        <text><![CDATA[收到短信的，上网上银行，输入错误密码，三次后锁定银行卡。]]></text>
        <time><![CDATA[2011-04-08 15:06:01]]></time>
    </status>

    <status>
        <text><![CDATA[@躺糖都瘦了..你是我爷们儿你不能朝三暮四啊大锅盖儿]]></text>
        <time><![CDATA[2011-04-08 15:05:01]]></time>
    </status>

    <status>
        <text><![CDATA[@楼下那位~依然建议发到豆瓣团购叉烧饭小组~]]></text>
        <time><![CDATA[2011-04-08 15:04:01]]></time>
    </status>

    <status>
        <text><![CDATA[收一短信【农行6228481190550642118唐璐  +8613030038614】，我要怎弄？？？]]></text>
        <time><![CDATA[2011-04-08 15:03:02]]></time>
    </status>

    <status>
        <text><![CDATA[明天还要6点滚去学车！你妹！怎么可能起得来！滚床单啊~]]></text>
        <time><![CDATA[2011-04-08 14:49:01]]></time>
    </status>

    <status>
        <text><![CDATA[一爷们让我跟他参加足球比赛 说“我和你拼抢，贴身拼抢，贴身盯人” 这神马意思 好基友么]]></text>
        <time><![CDATA[2011-04-08 14:43:01]]></time>
    </status>

    <status>
        <text><![CDATA[应该怀着什么心情背党章？刚吃的夜宵会吐出来吧！]]></text>
        <time><![CDATA[2011-04-08 14:23:02]]></time>
    </status>

    <status>
        <text><![CDATA[淫淫网感觉各种晒得,需被氪金狗眼啊= =... 转@神秘树洞我觉得没几个饭友会喜欢人人的。转@神秘树洞哥非常不喜欢校内，08年注销了就再也没玩过 转@神秘树洞饭友们，请问不玩校内玩饭否的人是不是很孤僻啊？有没有饭友讨厌人人网的？]]></text>
        <time><![CDATA[2011-04-08 14:20:02]]></time>
    </status>

    <status>
        <text><![CDATA[我吕盆友不仅说我是古代美女还嘲笑我胸部有B cup呜呜呜呜]]></text>
        <time><![CDATA[2011-04-08 14:10:03]]></time>
    </status>
</timelime>